{"otherData": {},"traceEvents":[{"cat":"function","dur":188519,"name":"void __cdecl WindowManager::createWindow(void)","ph":"X","pid":0,"tid":3659143759,"ts":245269342999},{"cat":"function","dur":95486,"name":"void __cdecl WindowManager::createInstance(void)","ph":"X","pid":0,"tid":3659143759,"ts":245269531691},{"cat":"function","dur":84,"name":"void __cdecl WindowManager::createSurface(void)","ph":"X","pid":0,"tid":3659143759,"ts":245269627242},{"cat":"function","dur":58,"name":"struct QueueFamilyIndices __cdecl GPUSelector::gpuQueueFamilies(class vk::PhysicalDevice,class vk::SurfaceKHR)","ph":"X","pid":0,"tid":3659143759,"ts":245269627678},{"cat":"function","dur":11261,"name":"struct SwapChainSupportDetails __cdecl GPUSelector::querySwapChainSupport(class vk::PhysicalDevice,class vk::SurfaceKHR)","ph":"X","pid":0,"tid":3659143759,"ts":245269627767},{"cat":"function","dur":11671,"name":"bool __cdecl GPUSelector::gpuSutable(const class vk::PhysicalDevice,class vk::SurfaceKHR)","ph":"X","pid":0,"tid":3659143759,"ts":245269627433},{"cat":"function","dur":11790,"name":"class vk::PhysicalDevice __cdecl GPUSelector::primaryGPU(class vk::Instance,class vk::SurfaceKHR)","ph":"X","pid":0,"tid":3659143759,"ts":245269627354},{"cat":"function","dur":28,"name":"struct QueueFamilyIndices __cdecl GPUSelector::gpuQueueFamilies(class vk::PhysicalDevice,class vk::SurfaceKHR)","ph":"X","pid":0,"tid":3659143759,"ts":245269639188},{"cat":"function","dur":99418,"name":"void __cdecl WindowManager::createDevice(void)","ph":"X","pid":0,"tid":3659143759,"ts":245269627352},{"cat":"function","dur":2142,"name":"struct SwapChainSupportDetails __cdecl GPUSelector::querySwapChainSupport(class vk::PhysicalDevice,class vk::SurfaceKHR)","ph":"X","pid":0,"tid":3659143759,"ts":245269727033},{"cat":"function","dur":0,"name":"struct vk::SurfaceFormatKHR __cdecl GPUSelector::chooseSwapSurfaceFormat(const class std::vector<struct vk::SurfaceFormatKHR,class std::allocator<struct vk::SurfaceFormatKHR> > &)","ph":"X","pid":0,"tid":3659143759,"ts":245269729222},{"cat":"function","dur":0,"name":"enum vk::PresentModeKHR __cdecl GPUSelector::chooseSwapPresentMode(const class std::vector<enum vk::PresentModeKHR,class std::allocator<enum vk::PresentModeKHR> > &)","ph":"X","pid":0,"tid":3659143759,"ts":245269729250},{"cat":"function","dur":0,"name":"struct VkExtent2D __cdecl GPUSelector::chooseSwapExtent(const struct VkSurfaceCapabilitiesKHR &,struct GLFWwindow *)","ph":"X","pid":0,"tid":3659143759,"ts":245269729272},{"cat":"function","dur":13048,"name":"void __cdecl WindowManager::createSwapchain(void)","ph":"X","pid":0,"tid":3659143759,"ts":245269727032},{"cat":"function","dur":72,"name":"void __cdecl WindowManager::createSwapchainImageViews(void)","ph":"X","pid":0,"tid":3659143759,"ts":245269740144},{"cat":"function","dur":54,"name":"void __cdecl WindowManager::createFramebuffers(void)","ph":"X","pid":0,"tid":3659143759,"ts":245269747492},{"cat":"function","dur":79,"name":"void __cdecl WindowManager::createSemaphores(void)","ph":"X","pid":0,"tid":3659143759,"ts":245269747595},{"cat":"function","dur":404708,"name":"__cdecl WindowManager::WindowManager(void)","ph":"X","pid":0,"tid":3659143759,"ts":245269342998},{"cat":"function","dur":7510,"name":"void __cdecl Renderer::createDescriptorPoolAndSets(void)","ph":"X","pid":0,"tid":3659143759,"ts":245269775162},{"cat":"function","dur":34997,"name":"void __cdecl Renderer::createRenderResources(void)","ph":"X","pid":0,"tid":3659143759,"ts":245269747757},{"cat":"function","dur":3835,"name":"void __cdecl Renderer::createStaticRenderCommands(void)","ph":"X","pid":0,"tid":3659143759,"ts":245269782793},{"cat":"function","dur":81,"name":"void __cdecl VkHelpers::createPoolsAndCommandBufffers(class vk::Device,class std::vector<class vk::CommandPool,class std::allocator<class vk::CommandPool> > &,class std::vector<class vk::CommandBuffer,class std::allocator<class vk::CommandBuffer> > &,unsigned int,unsigned int,enum vk::CommandBufferLevel)","ph":"X","pid":0,"tid":3659143759,"ts":245269786683},{"cat":"function","dur":39060,"name":"__cdecl Renderer::Renderer(class vk::Device &,class vk::PhysicalDevice &,class WindowManager &)","ph":"X","pid":0,"tid":3659143759,"ts":245269747757},{"cat":"function","dur":63,"name":"void __cdecl VkHelpers::createPoolsAndCommandBufffers(class vk::Device,class std::vector<class vk::CommandPool,class std::allocator<class vk::CommandPool> > &,class std::vector<class vk::CommandBuffer,class std::allocator<class vk::CommandBuffer> > &,unsigned int,unsigned int,enum vk::CommandBufferLevel)","ph":"X","pid":0,"tid":3659143759,"ts":245269786965},{"cat":"function","dur":97,"name":"void __cdecl TerrainSystem::CreateRenderResources(void)","ph":"X","pid":0,"tid":3659143759,"ts":245269786964},{"cat":"function","dur":309,"name":"struct Mesh *__cdecl TerrainMeshLoader::createChunkMesh(const class TerrainQuadTreeNode &)","ph":"X","pid":0,"tid":3659143759,"ts":245269787089},{"cat":"function","dur":14,"name":"void __cdecl BindlessMeshBuffer::writeMeshToBuffer(unsigned __int64,unsigned __int64,struct Mesh *,bool)","ph":"X","pid":0,"tid":3659143759,"ts":245269787423},{"cat":"function","dur":399,"name":"void __cdecl TerrainSystem::drawChunk(class TerrainQuadTreeNode *)","ph":"X","pid":0,"tid":3659143759,"ts":245269787088},{"cat":"function","dur":319,"name":"struct Mesh *__cdecl TerrainMeshLoader::createChunkMesh(const class TerrainQuadTreeNode &)","ph":"X","pid":0,"tid":3659143759,"ts":245269787512},{"cat":"function","dur":10,"name":"void __cdecl BindlessMeshBuffer::writeMeshToBuffer(unsigned __int64,unsigned __int64,struct Mesh *,bool)","ph":"X","pid":0,"tid":3659143759,"ts":245269787860},{"cat":"function","dur":395,"name":"void __cdecl TerrainSystem::drawChunk(class TerrainQuadTreeNode *)","ph":"X","pid":0,"tid":3659143759,"ts":245269787512},{"cat":"function","dur":300,"name":"struct Mesh *__cdecl TerrainMeshLoader::createChunkMesh(const class TerrainQuadTreeNode &)","ph":"X","pid":0,"tid":3659143759,"ts":245269787931},{"cat":"function","dur":9,"name":"void __cdecl BindlessMeshBuffer::writeMeshToBuffer(unsigned __int64,unsigned __int64,struct Mesh *,bool)","ph":"X","pid":0,"tid":3659143759,"ts":245269788255},{"cat":"function","dur":369,"name":"void __cdecl TerrainSystem::drawChunk(class TerrainQuadTreeNode *)","ph":"X","pid":0,"tid":3659143759,"ts":245269787930},{"cat":"function","dur":307,"name":"struct Mesh *__cdecl TerrainMeshLoader::createChunkMesh(const class TerrainQuadTreeNode &)","ph":"X","pid":0,"tid":3659143759,"ts":245269788323},{"cat":"function","dur":9,"name":"void __cdecl BindlessMeshBuffer::writeMeshToBuffer(unsigned __int64,unsigned __int64,struct Mesh *,bool)","ph":"X","pid":0,"tid":3659143759,"ts":245269788654},{"cat":"function","dur":384,"name":"void __cdecl TerrainSystem::drawChunk(class TerrainQuadTreeNode *)","ph":"X","pid":0,"tid":3659143759,"ts":245269788323},{"cat":"function","dur":467,"name":"struct Mesh *__cdecl TerrainMeshLoader::createChunkMesh(const class TerrainQuadTreeNode &)","ph":"X","pid":0,"tid":3659143759,"ts":245269788767},{"cat":"function","dur":16,"name":"void __cdecl BindlessMeshBuffer::writeMeshToBuffer(unsigned __int64,unsigned __int64,struct Mesh *,bool)","ph":"X","pid":0,"tid":3659143759,"ts":245269789278},{"cat":"function","dur":586,"name":"void __cdecl TerrainSystem::drawChunk(class TerrainQuadTreeNode *)","ph":"X","pid":0,"tid":3659143759,"ts":245269788767},{"cat":"function","dur":473,"name":"struct Mesh *__cdecl TerrainMeshLoader::createChunkMesh(const class TerrainQuadTreeNode &)","ph":"X","pid":0,"tid":3659143759,"ts":245269789391},{"cat":"function","dur":13,"name":"void __cdecl BindlessMeshBuffer::writeMeshToBuffer(unsigned __int64,unsigned __int64,struct Mesh *,bool)","ph":"X","pid":0,"tid":3659143759,"ts":245269789903},{"cat":"function","dur":578,"name":"void __cdecl TerrainSystem::drawChunk(class TerrainQuadTreeNode *)","ph":"X","pid":0,"tid":3659143759,"ts":245269789391},{"cat":"function","dur":484,"name":"struct Mesh *__cdecl TerrainMeshLoader::createChunkMesh(const class TerrainQuadTreeNode &)","ph":"X","pid":0,"tid":3659143759,"ts":245269790004},{"cat":"function","dur":13,"name":"void __cdecl BindlessMeshBuffer::writeMeshToBuffer(unsigned __int64,unsigned __int64,struct Mesh *,bool)","ph":"X","pid":0,"tid":3659143759,"ts":245269790525},{"cat":"function","dur":592,"name":"void __cdecl TerrainSystem::drawChunk(class TerrainQuadTreeNode *)","ph":"X","pid":0,"tid":3659143759,"ts":245269790004},{"cat":"function","dur":472,"name":"struct Mesh *__cdecl TerrainMeshLoader::createChunkMesh(const class TerrainQuadTreeNode &)","ph":"X","pid":0,"tid":3659143759,"ts":245269790633},{"cat":"function","dur":13,"name":"void __cdecl BindlessMeshBuffer::writeMeshToBuffer(unsigned __int64,unsigned __int64,struct Mesh *,bool)","ph":"X","pid":0,"tid":3659143759,"ts":245269791144},{"cat":"function","dur":582,"name":"void __cdecl TerrainSystem::drawChunk(class TerrainQuadTreeNode *)","ph":"X","pid":0,"tid":3659143759,"ts":245269790632},{"cat":"function","dur":4308,"name":"__cdecl TerrainSystem::TerrainSystem(class Renderer *,struct glm::vec<3,double,0> *)","ph":"X","pid":0,"tid":3659143759,"ts":245269786963},{"cat":"function","dur":43564,"name":"__cdecl WorldScene::WorldScene(class WindowManager &)","ph":"X","pid":0,"tid":3659143759,"ts":245269747747}]}